{"metadata": {"cd_programa": "42004012022P1", "nm_programa": "COMPUTAÇÃO", "sg_ies": "FURG", "conceito_recente": 4}, "discentes": {"geral": {"distribuicao_grau_academico": [{"DS_GRAU_ACADEMICO_DISCENTE": "MESTRADO", "TOTAL": 578, "PERCENTUAL": 100.0}], "situacao_academica": [{"NM_SITUACAO_DISCENTE": "ABANDONOU", "TOTAL": 7, "PERCENTUAL": 1.21}, {"NM_SITUACAO_DISCENTE": "DESLIGADO", "TOTAL": 58, "PERCENTUAL": 10.03}, {"NM_SITUACAO_DISCENTE": "MATRICULADO", "TOTAL": 372, "PERCENTUAL": 64.36}, {"NM_SITUACAO_DISCENTE": "TITULADO", "TOTAL": 141, "PERCENTUAL": 24.39}], "internacionalizacao_nacionalidade": [{"DS_TIPO_NACIONALIDADE_DISCENTE": "BRASILEIRO", "TOTAL": 564, "PERCENTUAL": 97.58}, {"DS_TIPO_NACIONALIDADE_DISCENTE": "ESTRANGEIRO", "TOTAL": 14, "PERCENTUAL": 2.42}], "tempo_medio_titulacao": [{"DS_GRAU_ACADEMICO_DISCENTE": "MESTRADO", "MEDIA_MESES_TITULACAO": 28.1}], "tamanho_total_alunos_periodo": 578, "media_alunos_por_ano": 72.2, "faixa_etaria": [{"DS_FAIXA_ETARIA": "20 A 24 ANOS", "TOTAL": 73, "PERCENTUAL": 12.63}, {"DS_FAIXA_ETARIA": "25 A 29 ANOS", "TOTAL": 292, "PERCENTUAL": 50.52}, {"DS_FAIXA_ETARIA": "30 A 34 ANOS", "TOTAL": 92, "PERCENTUAL": 15.92}, {"DS_FAIXA_ETARIA": "35 A 39 ANOS", "TOTAL": 63, "PERCENTUAL": 10.9}, {"DS_FAIXA_ETARIA": "40 A 44 ANOS", "TOTAL": 28, "PERCENTUAL": 4.84}, {"DS_FAIXA_ETARIA": "45 A 49 ANOS", "TOTAL": 15, "PERCENTUAL": 2.6}, {"DS_FAIXA_ETARIA": "50 A 54 ANOS", "TOTAL": 14, "PERCENTUAL": 2.42}, {"DS_FAIXA_ETARIA": "55 A 59 ANOS", "TOTAL": 1, "PERCENTUAL": 0.17}]}, "por_ano": {"2017": {"distribuicao_grau_academico": [{"DS_GRAU_ACADEMICO_DISCENTE": "MESTRADO", "TOTAL": 80, "PERCENTUAL": 100.0}], "situacao_academica": [{"NM_SITUACAO_DISCENTE": "DESLIGADO", "TOTAL": 3, "PERCENTUAL": 3.75}, {"NM_SITUACAO_DISCENTE": "MATRICULADO", "TOTAL": 55, "PERCENTUAL": 68.75}, {"NM_SITUACAO_DISCENTE": "TITULADO", "TOTAL": 22, "PERCENTUAL": 27.5}], "internacionalizacao_nacionalidade": [{"DS_TIPO_NACIONALIDADE_DISCENTE": "BRASILEIRO", "TOTAL": 79, "PERCENTUAL": 98.75}, {"DS_TIPO_NACIONALIDADE_DISCENTE": "ESTRANGEIRO", "TOTAL": 1, "PERCENTUAL": 1.25}], "tempo_medio_titulacao": [{"DS_GRAU_ACADEMICO_DISCENTE": "MESTRADO", "MEDIA_MESES_TITULACAO": 26.4}], "tamanho_total_alunos_periodo": 80, "media_alunos_por_ano": 80.0, "faixa_etaria": [{"DS_FAIXA_ETARIA": "20 A 24 ANOS", "TOTAL": 11, "PERCENTUAL": 13.75}, {"DS_FAIXA_ETARIA": "25 A 29 ANOS", "TOTAL": 39, "PERCENTUAL": 48.75}, {"DS_FAIXA_ETARIA": "30 A 34 ANOS", "TOTAL": 16, "PERCENTUAL": 20.0}, {"DS_FAIXA_ETARIA": "35 A 39 ANOS", "TOTAL": 7, "PERCENTUAL": 8.75}, {"DS_FAIXA_ETARIA": "40 A 44 ANOS", "TOTAL": 4, "PERCENTUAL": 5.0}, {"DS_FAIXA_ETARIA": "50 A 54 ANOS", "TOTAL": 2, "PERCENTUAL": 2.5}, {"DS_FAIXA_ETARIA": "55 A 59 ANOS", "TOTAL": 1, "PERCENTUAL": 1.25}]}, "2018": {"distribuicao_grau_academico": [{"DS_GRAU_ACADEMICO_DISCENTE": "MESTRADO", "TOTAL": 87, "PERCENTUAL": 100.0}], "situacao_academica": [{"NM_SITUACAO_DISCENTE": "DESLIGADO", "TOTAL": 6, "PERCENTUAL": 6.9}, {"NM_SITUACAO_DISCENTE": "MATRICULADO", "TOTAL": 54, "PERCENTUAL": 62.07}, {"NM_SITUACAO_DISCENTE": "TITULADO", "TOTAL": 27, "PERCENTUAL": 31.03}], "internacionalizacao_nacionalidade": [{"DS_TIPO_NACIONALIDADE_DISCENTE": "BRASILEIRO", "TOTAL": 86, "PERCENTUAL": 98.85}, {"DS_TIPO_NACIONALIDADE_DISCENTE": "ESTRANGEIRO", "TOTAL": 1, "PERCENTUAL": 1.15}], "tempo_medio_titulacao": [{"DS_GRAU_ACADEMICO_DISCENTE": "MESTRADO", "MEDIA_MESES_TITULACAO": 26.2}], "tamanho_total_alunos_periodo": 87, "media_alunos_por_ano": 87.0, "faixa_etaria": [{"DS_FAIXA_ETARIA": "20 A 24 ANOS", "TOTAL": 12, "PERCENTUAL": 13.79}, {"DS_FAIXA_ETARIA": "25 A 29 ANOS", "TOTAL": 41, "PERCENTUAL": 47.13}, {"DS_FAIXA_ETARIA": "30 A 34 ANOS", "TOTAL": 12, "PERCENTUAL": 13.79}, {"DS_FAIXA_ETARIA": "35 A 39 ANOS", "TOTAL": 10, "PERCENTUAL": 11.49}, {"DS_FAIXA_ETARIA": "40 A 44 ANOS", "TOTAL": 7, "PERCENTUAL": 8.05}, {"DS_FAIXA_ETARIA": "45 A 49 ANOS", "TOTAL": 3, "PERCENTUAL": 3.45}, {"DS_FAIXA_ETARIA": "50 A 54 ANOS", "TOTAL": 2, "PERCENTUAL": 2.3}]}, "2019": {"distribuicao_grau_academico": [{"DS_GRAU_ACADEMICO_DISCENTE": "MESTRADO", "TOTAL": 83, "PERCENTUAL": 100.0}], "situacao_academica": [{"NM_SITUACAO_DISCENTE": "ABANDONOU", "TOTAL": 7, "PERCENTUAL": 8.43}, {"NM_SITUACAO_DISCENTE": "DESLIGADO", "TOTAL": 9, "PERCENTUAL": 10.84}, {"NM_SITUACAO_DISCENTE": "MATRICULADO", "TOTAL": 47, "PERCENTUAL": 56.63}, {"NM_SITUACAO_DISCENTE": "TITULADO", "TOTAL": 20, "PERCENTUAL": 24.1}], "internacionalizacao_nacionalidade": [{"DS_TIPO_NACIONALIDADE_DISCENTE": "BRASILEIRO", "TOTAL": 81, "PERCENTUAL": 97.59}, {"DS_TIPO_NACIONALIDADE_DISCENTE": "ESTRANGEIRO", "TOTAL": 2, "PERCENTUAL": 2.41}], "tempo_medio_titulacao": [{"DS_GRAU_ACADEMICO_DISCENTE": "MESTRADO", "MEDIA_MESES_TITULACAO": 28.8}], "tamanho_total_alunos_periodo": 83, "media_alunos_por_ano": 83.0, "faixa_etaria": [{"DS_FAIXA_ETARIA": "20 A 24 ANOS", "TOTAL": 13, "PERCENTUAL": 15.66}, {"DS_FAIXA_ETARIA": "25 A 29 ANOS", "TOTAL": 35, "PERCENTUAL": 42.17}, {"DS_FAIXA_ETARIA": "30 A 34 ANOS", "TOTAL": 16, "PERCENTUAL": 19.28}, {"DS_FAIXA_ETARIA": "35 A 39 ANOS", "TOTAL": 10, "PERCENTUAL": 12.05}, {"DS_FAIXA_ETARIA": "40 A 44 ANOS", "TOTAL": 5, "PERCENTUAL": 6.02}, {"DS_FAIXA_ETARIA": "45 A 49 ANOS", "TOTAL": 2, "PERCENTUAL": 2.41}, {"DS_FAIXA_ETARIA": "50 A 54 ANOS", "TOTAL": 2, "PERCENTUAL": 2.41}]}, "2020": {"distribuicao_grau_academico": [{"DS_GRAU_ACADEMICO_DISCENTE": "MESTRADO", "TOTAL": 65, "PERCENTUAL": 100.0}], "situacao_academica": [{"NM_SITUACAO_DISCENTE": "DESLIGADO", "TOTAL": 8, "PERCENTUAL": 12.31}, {"NM_SITUACAO_DISCENTE": "MATRICULADO", "TOTAL": 42, "PERCENTUAL": 64.62}, {"NM_SITUACAO_DISCENTE": "TITULADO", "TOTAL": 15, "PERCENTUAL": 23.08}], "internacionalizacao_nacionalidade": [{"DS_TIPO_NACIONALIDADE_DISCENTE": "BRASILEIRO", "TOTAL": 64, "PERCENTUAL": 98.46}, {"DS_TIPO_NACIONALIDADE_DISCENTE": "ESTRANGEIRO", "TOTAL": 1, "PERCENTUAL": 1.54}], "tempo_medio_titulacao": [{"DS_GRAU_ACADEMICO_DISCENTE": "MESTRADO", "MEDIA_MESES_TITULACAO": 25.9}], "tamanho_total_alunos_periodo": 65, "media_alunos_por_ano": 65.0, "faixa_etaria": [{"DS_FAIXA_ETARIA": "20 A 24 ANOS", "TOTAL": 7, "PERCENTUAL": 10.77}, {"DS_FAIXA_ETARIA": "25 A 29 ANOS", "TOTAL": 37, "PERCENTUAL": 56.92}, {"DS_FAIXA_ETARIA": "30 A 34 ANOS", "TOTAL": 11, "PERCENTUAL": 16.92}, {"DS_FAIXA_ETARIA": "35 A 39 ANOS", "TOTAL": 6, "PERCENTUAL": 9.23}, {"DS_FAIXA_ETARIA": "40 A 44 ANOS", "TOTAL": 2, "PERCENTUAL": 3.08}, {"DS_FAIXA_ETARIA": "45 A 49 ANOS", "TOTAL": 2, "PERCENTUAL": 3.08}]}, "2021": {"distribuicao_grau_academico": [{"DS_GRAU_ACADEMICO_DISCENTE": "MESTRADO", "TOTAL": 62, "PERCENTUAL": 100.0}], "situacao_academica": [{"NM_SITUACAO_DISCENTE": "DESLIGADO", "TOTAL": 6, "PERCENTUAL": 9.68}, {"NM_SITUACAO_DISCENTE": "MATRICULADO", "TOTAL": 38, "PERCENTUAL": 61.29}, {"NM_SITUACAO_DISCENTE": "TITULADO", "TOTAL": 18, "PERCENTUAL": 29.03}], "internacionalizacao_nacionalidade": [{"DS_TIPO_NACIONALIDADE_DISCENTE": "BRASILEIRO", "TOTAL": 60, "PERCENTUAL": 96.77}, {"DS_TIPO_NACIONALIDADE_DISCENTE": "ESTRANGEIRO", "TOTAL": 2, "PERCENTUAL": 3.23}], "tempo_medio_titulacao": [{"DS_GRAU_ACADEMICO_DISCENTE": "MESTRADO", "MEDIA_MESES_TITULACAO": 28.3}], "tamanho_total_alunos_periodo": 62, "media_alunos_por_ano": 62.0, "faixa_etaria": [{"DS_FAIXA_ETARIA": "20 A 24 ANOS", "TOTAL": 8, "PERCENTUAL": 12.9}, {"DS_FAIXA_ETARIA": "25 A 29 ANOS", "TOTAL": 35, "PERCENTUAL": 56.45}, {"DS_FAIXA_ETARIA": "30 A 34 ANOS", "TOTAL": 8, "PERCENTUAL": 12.9}, {"DS_FAIXA_ETARIA": "35 A 39 ANOS", "TOTAL": 9, "PERCENTUAL": 14.52}, {"DS_FAIXA_ETARIA": "40 A 44 ANOS", "TOTAL": 2, "PERCENTUAL": 3.23}]}, "2022": {"distribuicao_grau_academico": [{"DS_GRAU_ACADEMICO_DISCENTE": "MESTRADO", "TOTAL": 60, "PERCENTUAL": 100.0}], "situacao_academica": [{"NM_SITUACAO_DISCENTE": "DESLIGADO", "TOTAL": 5, "PERCENTUAL": 8.33}, {"NM_SITUACAO_DISCENTE": "MATRICULADO", "TOTAL": 44, "PERCENTUAL": 73.33}, {"NM_SITUACAO_DISCENTE": "TITULADO", "TOTAL": 11, "PERCENTUAL": 18.33}], "internacionalizacao_nacionalidade": [{"DS_TIPO_NACIONALIDADE_DISCENTE": "BRASILEIRO", "TOTAL": 58, "PERCENTUAL": 96.67}, {"DS_TIPO_NACIONALIDADE_DISCENTE": "ESTRANGEIRO", "TOTAL": 2, "PERCENTUAL": 3.33}], "tempo_medio_titulacao": [{"DS_GRAU_ACADEMICO_DISCENTE": "MESTRADO", "MEDIA_MESES_TITULACAO": 30.3}], "tamanho_total_alunos_periodo": 60, "media_alunos_por_ano": 60.0, "faixa_etaria": [{"DS_FAIXA_ETARIA": "20 A 24 ANOS", "TOTAL": 3, "PERCENTUAL": 5.0}, {"DS_FAIXA_ETARIA": "25 A 29 ANOS", "TOTAL": 36, "PERCENTUAL": 60.0}, {"DS_FAIXA_ETARIA": "30 A 34 ANOS", "TOTAL": 8, "PERCENTUAL": 13.33}, {"DS_FAIXA_ETARIA": "35 A 39 ANOS", "TOTAL": 7, "PERCENTUAL": 11.67}, {"DS_FAIXA_ETARIA": "40 A 44 ANOS", "TOTAL": 2, "PERCENTUAL": 3.33}, {"DS_FAIXA_ETARIA": "45 A 49 ANOS", "TOTAL": 2, "PERCENTUAL": 3.33}, {"DS_FAIXA_ETARIA": "50 A 54 ANOS", "TOTAL": 2, "PERCENTUAL": 3.33}]}, "2023": {"distribuicao_grau_academico": [{"DS_GRAU_ACADEMICO_DISCENTE": "MESTRADO", "TOTAL": 66, "PERCENTUAL": 100.0}], "situacao_academica": [{"NM_SITUACAO_DISCENTE": "DESLIGADO", "TOTAL": 5, "PERCENTUAL": 7.58}, {"NM_SITUACAO_DISCENTE": "MATRICULADO", "TOTAL": 46, "PERCENTUAL": 69.7}, {"NM_SITUACAO_DISCENTE": "TITULADO", "TOTAL": 15, "PERCENTUAL": 22.73}], "internacionalizacao_nacionalidade": [{"DS_TIPO_NACIONALIDADE_DISCENTE": "BRASILEIRO", "TOTAL": 64, "PERCENTUAL": 96.97}, {"DS_TIPO_NACIONALIDADE_DISCENTE": "ESTRANGEIRO", "TOTAL": 2, "PERCENTUAL": 3.03}], "tempo_medio_titulacao": [{"DS_GRAU_ACADEMICO_DISCENTE": "MESTRADO", "MEDIA_MESES_TITULACAO": 29.5}], "tamanho_total_alunos_periodo": 66, "media_alunos_por_ano": 66.0, "faixa_etaria": [{"DS_FAIXA_ETARIA": "20 A 24 ANOS", "TOTAL": 6, "PERCENTUAL": 9.09}, {"DS_FAIXA_ETARIA": "25 A 29 ANOS", "TOTAL": 31, "PERCENTUAL": 46.97}, {"DS_FAIXA_ETARIA": "30 A 34 ANOS", "TOTAL": 10, "PERCENTUAL": 15.15}, {"DS_FAIXA_ETARIA": "35 A 39 ANOS", "TOTAL": 9, "PERCENTUAL": 13.64}, {"DS_FAIXA_ETARIA": "40 A 44 ANOS", "TOTAL": 4, "PERCENTUAL": 6.06}, {"DS_FAIXA_ETARIA": "45 A 49 ANOS", "TOTAL": 3, "PERCENTUAL": 4.55}, {"DS_FAIXA_ETARIA": "50 A 54 ANOS", "TOTAL": 3, "PERCENTUAL": 4.55}]}, "2024": {"distribuicao_grau_academico": [{"DS_GRAU_ACADEMICO_DISCENTE": "MESTRADO", "TOTAL": 75, "PERCENTUAL": 100.0}], "situacao_academica": [{"NM_SITUACAO_DISCENTE": "DESLIGADO", "TOTAL": 16, "PERCENTUAL": 21.33}, {"NM_SITUACAO_DISCENTE": "MATRICULADO", "TOTAL": 46, "PERCENTUAL": 61.33}, {"NM_SITUACAO_DISCENTE": "TITULADO", "TOTAL": 13, "PERCENTUAL": 17.33}], "internacionalizacao_nacionalidade": [{"DS_TIPO_NACIONALIDADE_DISCENTE": "BRASILEIRO", "TOTAL": 72, "PERCENTUAL": 96.0}, {"DS_TIPO_NACIONALIDADE_DISCENTE": "ESTRANGEIRO", "TOTAL": 3, "PERCENTUAL": 4.0}], "tempo_medio_titulacao": [{"DS_GRAU_ACADEMICO_DISCENTE": "MESTRADO", "MEDIA_MESES_TITULACAO": 32.9}], "tamanho_total_alunos_periodo": 75, "media_alunos_por_ano": 75.0, "faixa_etaria": [{"DS_FAIXA_ETARIA": "20 A 24 ANOS", "TOTAL": 13, "PERCENTUAL": 17.33}, {"DS_FAIXA_ETARIA": "25 A 29 ANOS", "TOTAL": 38, "PERCENTUAL": 50.67}, {"DS_FAIXA_ETARIA": "30 A 34 ANOS", "TOTAL": 11, "PERCENTUAL": 14.67}, {"DS_FAIXA_ETARIA": "35 A 39 ANOS", "TOTAL": 5, "PERCENTUAL": 6.67}, {"DS_FAIXA_ETARIA": "40 A 44 ANOS", "TOTAL": 2, "PERCENTUAL": 2.67}, {"DS_FAIXA_ETARIA": "45 A 49 ANOS", "TOTAL": 3, "PERCENTUAL": 4.0}, {"DS_FAIXA_ETARIA": "50 A 54 ANOS", "TOTAL": 3, "PERCENTUAL": 4.0}]}}}, "docentes": {"geral": {"lideranca_bolsas_pq": [{"TEM_BOLSA_PQ": "NÃO", "TOTAL": 126, "PERCENTUAL": 85.71}, {"TEM_BOLSA_PQ": "SIM", "TOTAL": 21, "PERCENTUAL": 14.29}], "internacionalizacao_titulacao_exterior": [{"TITULADO_NO_EXTERIOR": "NÃO", "TOTAL": 125, "PERCENTUAL": 85.03}, {"TITULADO_NO_EXTERIOR": "SIM", "TOTAL": 22, "PERCENTUAL": 14.97}], "internacionalizacao_nacionalidade": [{"DOCENTE_ESTRANGEIRO": "BRASILEIRO", "TOTAL": 147, "PERCENTUAL": 100.0}], "endogamia_academica": [{"ENDOGAMIA": "NÃO", "TOTAL": 147, "PERCENTUAL": 100.0}], "maturidade_media_anos_doutorado": 11.3, "categoria_docente": [{"DS_CATEGORIA_DOCENTE": "COLABORADOR", "TOTAL": 18, "PERCENTUAL": 10.78}, {"DS_CATEGORIA_DOCENTE": "PERMANENTE", "TOTAL": 147, "PERCENTUAL": 88.02}, {"DS_CATEGORIA_DOCENTE": "VISITANTE", "TOTAL": 2, "PERCENTUAL": 1.2}], "regime_trabalho": [{"DS_REGIME_TRABALHO": "DEDICAÇÃO EXCLUSIVA", "TOTAL": 26, "PERCENTUAL": 17.69}, {"DS_REGIME_TRABALHO": "INTEGRAL", "TOTAL": 119, "PERCENTUAL": 80.95}, {"DS_REGIME_TRABALHO": "PARCIAL", "TOTAL": 2, "PERCENTUAL": 1.36}]}, "por_ano": {"2017": {"lideranca_bolsas_pq": [{"TEM_BOLSA_PQ": "NÃO", "TOTAL": 21, "PERCENTUAL": 87.5}, {"TEM_BOLSA_PQ": "SIM", "TOTAL": 3, "PERCENTUAL": 12.5}], "internacionalizacao_titulacao_exterior": [{"TITULADO_NO_EXTERIOR": "NÃO", "TOTAL": 21, "PERCENTUAL": 87.5}, {"TITULADO_NO_EXTERIOR": "SIM", "TOTAL": 3, "PERCENTUAL": 12.5}], "internacionalizacao_nacionalidade": [{"DOCENTE_ESTRANGEIRO": "BRASILEIRO", "TOTAL": 24, "PERCENTUAL": 100.0}], "endogamia_academica": [{"ENDOGAMIA": "NÃO", "TOTAL": 24, "PERCENTUAL": 100.0}], "maturidade_media_anos_doutorado": 8.4, "categoria_docente": [{"DS_CATEGORIA_DOCENTE": "COLABORADOR", "TOTAL": 1, "PERCENTUAL": 4.0}, {"DS_CATEGORIA_DOCENTE": "PERMANENTE", "TOTAL": 24, "PERCENTUAL": 96.0}], "regime_trabalho": [{"DS_REGIME_TRABALHO": "DEDICAÇÃO EXCLUSIVA", "TOTAL": 3, "PERCENTUAL": 12.5}, {"DS_REGIME_TRABALHO": "INTEGRAL", "TOTAL": 20, "PERCENTUAL": 83.33}, {"DS_REGIME_TRABALHO": "PARCIAL", "TOTAL": 1, "PERCENTUAL": 4.17}]}, "2018": {"lideranca_bolsas_pq": [{"TEM_BOLSA_PQ": "NÃO", "TOTAL": 22, "PERCENTUAL": 88.0}, {"TEM_BOLSA_PQ": "SIM", "TOTAL": 3, "PERCENTUAL": 12.0}], "internacionalizacao_titulacao_exterior": [{"TITULADO_NO_EXTERIOR": "NÃO", "TOTAL": 22, "PERCENTUAL": 88.0}, {"TITULADO_NO_EXTERIOR": "SIM", "TOTAL": 3, "PERCENTUAL": 12.0}], "internacionalizacao_nacionalidade": [{"DOCENTE_ESTRANGEIRO": "BRASILEIRO", "TOTAL": 25, "PERCENTUAL": 100.0}], "endogamia_academica": [{"ENDOGAMIA": "NÃO", "TOTAL": 25, "PERCENTUAL": 100.0}], "maturidade_media_anos_doutorado": 9.1, "categoria_docente": [{"DS_CATEGORIA_DOCENTE": "COLABORADOR", "TOTAL": 1, "PERCENTUAL": 3.85}, {"DS_CATEGORIA_DOCENTE": "PERMANENTE", "TOTAL": 25, "PERCENTUAL": 96.15}], "regime_trabalho": [{"DS_REGIME_TRABALHO": "DEDICAÇÃO EXCLUSIVA", "TOTAL": 3, "PERCENTUAL": 12.0}, {"DS_REGIME_TRABALHO": "INTEGRAL", "TOTAL": 21, "PERCENTUAL": 84.0}, {"DS_REGIME_TRABALHO": "PARCIAL", "TOTAL": 1, "PERCENTUAL": 4.0}]}, "2019": {"lideranca_bolsas_pq": [{"TEM_BOLSA_PQ": "NÃO", "TOTAL": 12, "PERCENTUAL": 80.0}, {"TEM_BOLSA_PQ": "SIM", "TOTAL": 3, "PERCENTUAL": 20.0}], "internacionalizacao_titulacao_exterior": [{"TITULADO_NO_EXTERIOR": "NÃO", "TOTAL": 13, "PERCENTUAL": 86.67}, {"TITULADO_NO_EXTERIOR": "SIM", "TOTAL": 2, "PERCENTUAL": 13.33}], "internacionalizacao_nacionalidade": [{"DOCENTE_ESTRANGEIRO": "BRASILEIRO", "TOTAL": 15, "PERCENTUAL": 100.0}], "endogamia_academica": [{"ENDOGAMIA": "NÃO", "TOTAL": 15, "PERCENTUAL": 100.0}], "maturidade_media_anos_doutorado": 9.9, "categoria_docente": [{"DS_CATEGORIA_DOCENTE": "COLABORADOR", "TOTAL": 1, "PERCENTUAL": 6.25}, {"DS_CATEGORIA_DOCENTE": "PERMANENTE", "TOTAL": 15, "PERCENTUAL": 93.75}], "regime_trabalho": [{"DS_REGIME_TRABALHO": "DEDICAÇÃO EXCLUSIVA", "TOTAL": 3, "PERCENTUAL": 20.0}, {"DS_REGIME_TRABALHO": "INTEGRAL", "TOTAL": 12, "PERCENTUAL": 80.0}]}, "2020": {"lideranca_bolsas_pq": [{"TEM_BOLSA_PQ": "NÃO", "TOTAL": 12, "PERCENTUAL": 80.0}, {"TEM_BOLSA_PQ": "SIM", "TOTAL": 3, "PERCENTUAL": 20.0}], "internacionalizacao_titulacao_exterior": [{"TITULADO_NO_EXTERIOR": "NÃO", "TOTAL": 13, "PERCENTUAL": 86.67}, {"TITULADO_NO_EXTERIOR": "SIM", "TOTAL": 2, "PERCENTUAL": 13.33}], "internacionalizacao_nacionalidade": [{"DOCENTE_ESTRANGEIRO": "BRASILEIRO", "TOTAL": 15, "PERCENTUAL": 100.0}], "endogamia_academica": [{"ENDOGAMIA": "NÃO", "TOTAL": 15, "PERCENTUAL": 100.0}], "maturidade_media_anos_doutorado": 10.9, "categoria_docente": [{"DS_CATEGORIA_DOCENTE": "PERMANENTE", "TOTAL": 15, "PERCENTUAL": 100.0}], "regime_trabalho": [{"DS_REGIME_TRABALHO": "DEDICAÇÃO EXCLUSIVA", "TOTAL": 3, "PERCENTUAL": 20.0}, {"DS_REGIME_TRABALHO": "INTEGRAL", "TOTAL": 12, "PERCENTUAL": 80.0}]}, "2021": {"lideranca_bolsas_pq": [{"TEM_BOLSA_PQ": "NÃO", "TOTAL": 17, "PERCENTUAL": 85.0}, {"TEM_BOLSA_PQ": "SIM", "TOTAL": 3, "PERCENTUAL": 15.0}], "internacionalizacao_titulacao_exterior": [{"TITULADO_NO_EXTERIOR": "NÃO", "TOTAL": 17, "PERCENTUAL": 85.0}, {"TITULADO_NO_EXTERIOR": "SIM", "TOTAL": 3, "PERCENTUAL": 15.0}], "internacionalizacao_nacionalidade": [{"DOCENTE_ESTRANGEIRO": "BRASILEIRO", "TOTAL": 20, "PERCENTUAL": 100.0}], "endogamia_academica": [{"ENDOGAMIA": "NÃO", "TOTAL": 20, "PERCENTUAL": 100.0}], "maturidade_media_anos_doutorado": 11.6, "categoria_docente": [{"DS_CATEGORIA_DOCENTE": "PERMANENTE", "TOTAL": 20, "PERCENTUAL": 100.0}], "regime_trabalho": [{"DS_REGIME_TRABALHO": "DEDICAÇÃO EXCLUSIVA", "TOTAL": 5, "PERCENTUAL": 25.0}, {"DS_REGIME_TRABALHO": "INTEGRAL", "TOTAL": 15, "PERCENTUAL": 75.0}]}, "2022": {"lideranca_bolsas_pq": [{"TEM_BOLSA_PQ": "NÃO", "TOTAL": 14, "PERCENTUAL": 87.5}, {"TEM_BOLSA_PQ": "SIM", "TOTAL": 2, "PERCENTUAL": 12.5}], "internacionalizacao_titulacao_exterior": [{"TITULADO_NO_EXTERIOR": "NÃO", "TOTAL": 13, "PERCENTUAL": 81.25}, {"TITULADO_NO_EXTERIOR": "SIM", "TOTAL": 3, "PERCENTUAL": 18.75}], "internacionalizacao_nacionalidade": [{"DOCENTE_ESTRANGEIRO": "BRASILEIRO", "TOTAL": 16, "PERCENTUAL": 100.0}], "endogamia_academica": [{"ENDOGAMIA": "NÃO", "TOTAL": 16, "PERCENTUAL": 100.0}], "maturidade_media_anos_doutorado": 13.3, "categoria_docente": [{"DS_CATEGORIA_DOCENTE": "COLABORADOR", "TOTAL": 5, "PERCENTUAL": 22.73}, {"DS_CATEGORIA_DOCENTE": "PERMANENTE", "TOTAL": 16, "PERCENTUAL": 72.73}, {"DS_CATEGORIA_DOCENTE": "VISITANTE", "TOTAL": 1, "PERCENTUAL": 4.55}], "regime_trabalho": [{"DS_REGIME_TRABALHO": "DEDICAÇÃO EXCLUSIVA", "TOTAL": 3, "PERCENTUAL": 18.75}, {"DS_REGIME_TRABALHO": "INTEGRAL", "TOTAL": 13, "PERCENTUAL": 81.25}]}, "2023": {"lideranca_bolsas_pq": [{"TEM_BOLSA_PQ": "NÃO", "TOTAL": 14, "PERCENTUAL": 87.5}, {"TEM_BOLSA_PQ": "SIM", "TOTAL": 2, "PERCENTUAL": 12.5}], "internacionalizacao_titulacao_exterior": [{"TITULADO_NO_EXTERIOR": "NÃO", "TOTAL": 13, "PERCENTUAL": 81.25}, {"TITULADO_NO_EXTERIOR": "SIM", "TOTAL": 3, "PERCENTUAL": 18.75}], "internacionalizacao_nacionalidade": [{"DOCENTE_ESTRANGEIRO": "BRASILEIRO", "TOTAL": 16, "PERCENTUAL": 100.0}], "endogamia_academica": [{"ENDOGAMIA": "NÃO", "TOTAL": 16, "PERCENTUAL": 100.0}], "maturidade_media_anos_doutorado": 14.3, "categoria_docente": [{"DS_CATEGORIA_DOCENTE": "COLABORADOR", "TOTAL": 5, "PERCENTUAL": 22.73}, {"DS_CATEGORIA_DOCENTE": "PERMANENTE", "TOTAL": 16, "PERCENTUAL": 72.73}, {"DS_CATEGORIA_DOCENTE": "VISITANTE", "TOTAL": 1, "PERCENTUAL": 4.55}], "regime_trabalho": [{"DS_REGIME_TRABALHO": "DEDICAÇÃO EXCLUSIVA", "TOTAL": 3, "PERCENTUAL": 18.75}, {"DS_REGIME_TRABALHO": "INTEGRAL", "TOTAL": 13, "PERCENTUAL": 81.25}]}, "2024": {"lideranca_bolsas_pq": [{"TEM_BOLSA_PQ": "NÃO", "TOTAL": 14, "PERCENTUAL": 87.5}, {"TEM_BOLSA_PQ": "SIM", "TOTAL": 2, "PERCENTUAL": 12.5}], "internacionalizacao_titulacao_exterior": [{"TITULADO_NO_EXTERIOR": "NÃO", "TOTAL": 13, "PERCENTUAL": 81.25}, {"TITULADO_NO_EXTERIOR": "SIM", "TOTAL": 3, "PERCENTUAL": 18.75}], "internacionalizacao_nacionalidade": [{"DOCENTE_ESTRANGEIRO": "BRASILEIRO", "TOTAL": 16, "PERCENTUAL": 100.0}], "endogamia_academica": [{"ENDOGAMIA": "NÃO", "TOTAL": 16, "PERCENTUAL": 100.0}], "maturidade_media_anos_doutorado": 15.3, "categoria_docente": [{"DS_CATEGORIA_DOCENTE": "COLABORADOR", "TOTAL": 5, "PERCENTUAL": 23.81}, {"DS_CATEGORIA_DOCENTE": "PERMANENTE", "TOTAL": 16, "PERCENTUAL": 76.19}], "regime_trabalho": [{"DS_REGIME_TRABALHO": "DEDICAÇÃO EXCLUSIVA", "TOTAL": 3, "PERCENTUAL": 18.75}, {"DS_REGIME_TRABALHO": "INTEGRAL", "TOTAL": 13, "PERCENTUAL": 81.25}]}}}}