{"metadata": {"cd_programa": "32008015011P7", "nm_programa": "INFORMÁTICA", "sg_ies": "PUC/MG", "conceito_recente": 4}, "radar": {"geral": {"valores_reais": {"total_docentes_permanentes": 95.0, "docentes_permanentes_por_programa": 95.0, "pct_docentes_permanentes": 100.0, "pct_pq": 38.94736842105263, "pct_titulado_no_exterior": 14.736842105263156, "pct_docente_estrangeiro": 4.2105263157894735, "pct_endogamia": 0.0, "pct_dedicacao_exclusiva": 0.0, "pct_instituicao_publica": 0.0, "media_anos_doutorado": 16.442105263157895, "discentes_por_programa": 559.0, "pct_mestrado": 66.54740608228981, "pct_doutorado": 33.452593917710196, "pct_titulado": 16.99463327370304, "taxa_evasao": 6.618962432915922, "pct_estrangeiro_discente": 100.0, "media_meses_titulacao_mestrado": 33.275, "media_meses_titulacao_doutorado": 65.0, "publicacoes_por_programa": 202.0}, "normalizado": {"total_docentes_permanentes": 0.0035587188612099642, "docentes_permanentes_por_programa": 1.0, "pct_docentes_permanentes": 1.0, "pct_pq": 0.6321182053494392, "pct_titulado_no_exterior": 0.14787715111166935, "pct_docente_estrangeiro": 0.6659100581642785, "pct_endogamia": 0.0, "pct_dedicacao_exclusiva": 0.0, "pct_instituicao_publica": 0.0, "media_anos_doutorado": 0.7139058171745153, "discentes_por_programa": 1.0, "pct_mestrado": 0.3471390726442196, "pct_doutorado": 0.6528609273557805, "pct_titulado": 0.38029244239378546, "taxa_evasao": 0.3167521410221183, "pct_estrangeiro_discente": 1.0, "media_meses_titulacao_mestrado": 0.4167867435158502, "media_meses_titulacao_doutorado": 0.9872611464968155, "publicacoes_por_programa": 1.0}}, "por_ano": {"2017": {"valores_reais": {"total_docentes_permanentes": 11.0, "docentes_permanentes_por_programa": 11.0, "pct_docentes_permanentes": 100.0, "pct_pq": 36.36363636363637, "pct_titulado_no_exterior": 9.090909090909092, "pct_docente_estrangeiro": 0.0, "pct_endogamia": 0.0, "pct_dedicacao_exclusiva": 0.0, "pct_instituicao_publica": 0.0, "media_anos_doutorado": 11.727272727272727, "discentes_por_programa": 61.0, "pct_mestrado": 73.77049180327869, "pct_doutorado": 26.229508196721312, "pct_titulado": 21.311475409836063, "taxa_evasao": 3.278688524590164, "pct_estrangeiro_discente": 100.0, "media_meses_titulacao_mestrado": 31.846153846153847, "media_meses_titulacao_doutorado": 0.0, "publicacoes_por_programa": 16.0}, "normalizado": {"total_docentes_permanentes": 0.0, "docentes_permanentes_por_programa": 0.0, "pct_docentes_permanentes": 1.0, "pct_pq": 0.5791728763040239, "pct_titulado_no_exterior": 0.0, "pct_docente_estrangeiro": 0.0, "pct_endogamia": 0.0, "pct_dedicacao_exclusiva": 0.0, "pct_instituicao_publica": 0.0, "media_anos_doutorado": 0.21760765550239225, "discentes_por_programa": 0.025424442261821247, "pct_mestrado": 0.4881048361295607, "pct_doutorado": 0.5118951638704393, "pct_titulado": 0.7479962018599714, "taxa_evasao": 0.0, "pct_estrangeiro_discente": 1.0, "media_meses_titulacao_mestrado": 0.31384393704278446, "media_meses_titulacao_doutorado": 0.0, "publicacoes_por_programa": 0.0}}, "2018": {"valores_reais": {"total_docentes_permanentes": 11.0, "docentes_permanentes_por_programa": 11.0, "pct_docentes_permanentes": 100.0, "pct_pq": 36.36363636363637, "pct_titulado_no_exterior": 9.090909090909092, "pct_docente_estrangeiro": 0.0, "pct_endogamia": 0.0, "pct_dedicacao_exclusiva": 0.0, "pct_instituicao_publica": 0.0, "media_anos_doutorado": 12.727272727272727, "discentes_por_programa": 70.0, "pct_mestrado": 71.42857142857143, "pct_doutorado": 28.57142857142857, "pct_titulado": 14.285714285714285, "taxa_evasao": 10.0, "pct_estrangeiro_discente": 100.0, "media_meses_titulacao_mestrado": 32.5, "media_meses_titulacao_doutorado": 0.0, "publicacoes_por_programa": 18.0}, "normalizado": {"total_docentes_permanentes": 0.0, "docentes_permanentes_por_programa": 0.0, "pct_docentes_permanentes": 1.0, "pct_pq": 0.5791728763040239, "pct_titulado_no_exterior": 0.0, "pct_docente_estrangeiro": 0.0, "pct_endogamia": 0.0, "pct_dedicacao_exclusiva": 0.0, "pct_instituicao_publica": 0.0, "media_anos_doutorado": 0.3228708133971291, "discentes_por_programa": 0.05068051073382911, "pct_mestrado": 0.4423999107839858, "pct_doutorado": 0.5576000892160142, "pct_titulado": 0.14954976880019466, "taxa_evasao": 0.6799140708915145, "pct_estrangeiro_discente": 1.0, "media_meses_titulacao_mestrado": 0.36095100864553326, "media_meses_titulacao_doutorado": 0.0, "publicacoes_por_programa": 0.007849978194505003}}, "2019": {"valores_reais": {"total_docentes_permanentes": 12.0, "docentes_permanentes_por_programa": 12.0, "pct_docentes_permanentes": 100.0, "pct_pq": 41.66666666666667, "pct_titulado_no_exterior": 16.666666666666664, "pct_docente_estrangeiro": 0.0, "pct_endogamia": 0.0, "pct_dedicacao_exclusiva": 0.0, "pct_instituicao_publica": 0.0, "media_anos_doutorado": 13.166666666666666, "discentes_por_programa": 73.0, "pct_mestrado": 68.4931506849315, "pct_doutorado": 31.506849315068493, "pct_titulado": 12.32876712328767, "taxa_evasao": 9.58904109589041, "pct_estrangeiro_discente": 100.0, "media_meses_titulacao_mestrado": 32.111111111111114, "media_meses_titulacao_doutorado": 0.0, "publicacoes_por_programa": 19.0}, "normalizado": {"total_docentes_permanentes": 0.0, "docentes_permanentes_por_programa": 0.0, "pct_docentes_permanentes": 1.0, "pct_pq": 0.6878415300546449, "pct_titulado_no_exterior": 0.20544948289578358, "pct_docente_estrangeiro": 0.0, "pct_endogamia": 0.0, "pct_dedicacao_exclusiva": 0.0, "pct_instituicao_publica": 0.0, "media_anos_doutorado": 0.3691228070175438, "discentes_por_programa": 0.05909920022449839, "pct_mestrado": 0.3851122303850802, "pct_doutorado": 0.6148877696149199, "pct_titulado": 0.0, "taxa_evasao": 0.6357724055736208, "pct_estrangeiro_discente": 1.0, "media_meses_titulacao_mestrado": 0.33293307716938875, "media_meses_titulacao_doutorado": 0.0, "publicacoes_por_programa": 0.01875272568687308}}, "2020": {"valores_reais": {"total_docentes_permanentes": 12.0, "docentes_permanentes_por_programa": 12.0, "pct_docentes_permanentes": 100.0, "pct_pq": 33.33333333333333, "pct_titulado_no_exterior": 16.666666666666664, "pct_docente_estrangeiro": 0.0, "pct_endogamia": 0.0, "pct_dedicacao_exclusiva": 0.0, "pct_instituicao_publica": 0.0, "media_anos_doutorado": 14.166666666666666, "discentes_por_programa": 73.0, "pct_mestrado": 64.38356164383562, "pct_doutorado": 35.61643835616438, "pct_titulado": 19.17808219178082, "taxa_evasao": 2.73972602739726, "pct_estrangeiro_discente": 100.0, "media_meses_titulacao_mestrado": 31.0, "media_meses_titulacao_doutorado": 48.0, "publicacoes_por_programa": 21.0}, "normalizado": {"total_docentes_permanentes": 0.0, "docentes_permanentes_por_programa": 0.0, "pct_docentes_permanentes": 1.0, "pct_pq": 0.5170765027322404, "pct_titulado_no_exterior": 0.20544948289578358, "pct_docente_estrangeiro": 0.0, "pct_endogamia": 0.0, "pct_dedicacao_exclusiva": 0.0, "pct_instituicao_publica": 0.0, "media_anos_doutorado": 0.47438596491228063, "discentes_por_programa": 0.05909920022449839, "pct_mestrado": 0.30490947782661243, "pct_doutorado": 0.6950905221733875, "pct_titulado": 0.5662761662504958, "taxa_evasao": 0.0, "pct_estrangeiro_discente": 1.0, "media_meses_titulacao_mestrado": 0.25288184438040356, "media_meses_titulacao_doutorado": 0.0, "publicacoes_por_programa": 0.04055822067160923}}, "2021": {"valores_reais": {"total_docentes_permanentes": 12.0, "docentes_permanentes_por_programa": 12.0, "pct_docentes_permanentes": 100.0, "pct_pq": 41.66666666666667, "pct_titulado_no_exterior": 16.666666666666664, "pct_docente_estrangeiro": 8.333333333333332, "pct_endogamia": 0.0, "pct_dedicacao_exclusiva": 0.0, "pct_instituicao_publica": 0.0, "media_anos_doutorado": 17.75, "discentes_por_programa": 80.0, "pct_mestrado": 65.0, "pct_doutorado": 35.0, "pct_titulado": 18.75, "taxa_evasao": 11.25, "pct_estrangeiro_discente": 100.0, "media_meses_titulacao_mestrado": 31.1, "media_meses_titulacao_doutorado": 56.4, "publicacoes_por_programa": 23.0}, "normalizado": {"total_docentes_permanentes": 0.0, "docentes_permanentes_por_programa": 0.0, "pct_docentes_permanentes": 1.0, "pct_pq": 0.6878415300546449, "pct_titulado_no_exterior": 0.20544948289578358, "pct_docente_estrangeiro": 1.0, "pct_endogamia": 0.0, "pct_dedicacao_exclusiva": 0.0, "pct_instituicao_publica": 0.0, "media_anos_doutorado": 0.851578947368421, "discentes_por_programa": 0.07874280903606005, "pct_mestrado": 0.31693989071038253, "pct_doutorado": 0.6830601092896175, "pct_titulado": 0.5298126064735946, "taxa_evasao": 0.8141783029001074, "pct_estrangeiro_discente": 1.0, "media_meses_titulacao_mestrado": 0.26008645533141234, "media_meses_titulacao_doutorado": 0.3025477707006368, "publicacoes_por_programa": 0.06236371565634539}}, "2022": {"valores_reais": {"total_docentes_permanentes": 12.0, "docentes_permanentes_por_programa": 12.0, "pct_docentes_permanentes": 100.0, "pct_pq": 41.66666666666667, "pct_titulado_no_exterior": 16.666666666666664, "pct_docente_estrangeiro": 8.333333333333332, "pct_endogamia": 0.0, "pct_dedicacao_exclusiva": 0.0, "pct_instituicao_publica": 0.0, "media_anos_doutorado": 19.25, "discentes_por_programa": 69.0, "pct_mestrado": 63.76811594202898, "pct_doutorado": 36.231884057971016, "pct_titulado": 11.594202898550725, "taxa_evasao": 7.246376811594203, "pct_estrangeiro_discente": 100.0, "media_meses_titulacao_mestrado": 39.714285714285715, "media_meses_titulacao_doutorado": 76.0, "publicacoes_por_programa": 23.0}, "normalizado": {"total_docentes_permanentes": 0.0, "docentes_permanentes_por_programa": 0.0, "pct_docentes_permanentes": 1.0, "pct_pq": 0.6878415300546449, "pct_titulado_no_exterior": 0.20544948289578358, "pct_docente_estrangeiro": 1.0, "pct_endogamia": 0.0, "pct_dedicacao_exclusiva": 0.0, "pct_instituicao_publica": 0.0, "media_anos_doutorado": 1.0, "discentes_por_programa": 0.04787428090360601, "pct_mestrado": 0.2928984375883876, "pct_doutorado": 0.7071015624116123, "pct_titulado": 0.0, "taxa_evasao": 0.38414358878562865, "pct_estrangeiro_discente": 1.0, "media_meses_titulacao_mestrado": 0.8807122272540142, "media_meses_titulacao_doutorado": 1.0, "publicacoes_por_programa": 0.06236371565634539}}, "2023": {"valores_reais": {"total_docentes_permanentes": 13.0, "docentes_permanentes_por_programa": 13.0, "pct_docentes_permanentes": 100.0, "pct_pq": 38.46153846153847, "pct_titulado_no_exterior": 15.384615384615385, "pct_docente_estrangeiro": 7.6923076923076925, "pct_endogamia": 0.0, "pct_dedicacao_exclusiva": 0.0, "pct_instituicao_publica": 0.0, "media_anos_doutorado": 20.53846153846154, "discentes_por_programa": 67.0, "pct_mestrado": 61.19402985074627, "pct_doutorado": 38.80597014925373, "pct_titulado": 16.417910447761194, "taxa_evasao": 5.970149253731343, "pct_estrangeiro_discente": 100.0, "media_meses_titulacao_mestrado": 33.0, "media_meses_titulacao_doutorado": 64.0, "publicacoes_por_programa": 31.0}, "normalizado": {"total_docentes_permanentes": 0.0, "docentes_permanentes_por_programa": 0.0, "pct_docentes_permanentes": 1.0, "pct_pq": 0.6221626733921817, "pct_titulado_no_exterior": 0.16720212961263087, "pct_docente_estrangeiro": 1.0, "pct_endogamia": 0.0, "pct_dedicacao_exclusiva": 0.0, "pct_instituicao_publica": 0.0, "media_anos_doutorado": 1.0, "discentes_por_programa": 0.04226182124315982, "pct_mestrado": 0.24266256539317466, "pct_doutorado": 0.7573374346068253, "pct_titulado": 0.33116784052480364, "taxa_evasao": 0.24706221844590148, "pct_estrangeiro_discente": 1.0, "media_meses_titulacao_mestrado": 0.3969740634005765, "media_meses_titulacao_doutorado": 0.9076433121019111, "publicacoes_por_programa": 0.14958569559529}}, "2024": {"valores_reais": {"total_docentes_permanentes": 12.0, "docentes_permanentes_por_programa": 12.0, "pct_docentes_permanentes": 100.0, "pct_pq": 41.66666666666667, "pct_titulado_no_exterior": 16.666666666666664, "pct_docente_estrangeiro": 8.333333333333332, "pct_endogamia": 0.0, "pct_dedicacao_exclusiva": 0.0, "pct_instituicao_publica": 0.0, "media_anos_doutorado": 21.166666666666668, "discentes_por_programa": 66.0, "pct_mestrado": 65.15151515151516, "pct_doutorado": 34.84848484848485, "pct_titulado": 22.727272727272727, "taxa_evasao": 1.5151515151515151, "pct_estrangeiro_discente": 100.0, "media_meses_titulacao_mestrado": 37.36363636363637, "media_meses_titulacao_doutorado": 78.25, "publicacoes_por_programa": 51.0}, "normalizado": {"total_docentes_permanentes": 0.0, "docentes_permanentes_por_programa": 0.0, "pct_docentes_permanentes": 1.0, "pct_pq": 0.6878415300546449, "pct_titulado_no_exterior": 0.20544948289578358, "pct_docente_estrangeiro": 1.0, "pct_endogamia": 0.0, "pct_dedicacao_exclusiva": 0.0, "pct_instituicao_publica": 0.0, "media_anos_doutorado": 1.0, "discentes_por_programa": 0.039455591412936725, "pct_mestrado": 0.31989686088046754, "pct_doutorado": 0.6801031391195326, "pct_titulado": 0.8685922254917144, "taxa_evasao": 0.0, "pct_estrangeiro_discente": 1.0, "media_meses_titulacao_mestrado": 0.7113570867173177, "media_meses_titulacao_doutorado": 1.0, "publicacoes_por_programa": 0.3676406454426515}}}}, "discentes": {"geral": {"distribuicao_grau_academico": [{"DS_GRAU_ACADEMICO_DISCENTE": "DOUTORADO", "TOTAL": 187, "PERCENTUAL": 33.45}, {"DS_GRAU_ACADEMICO_DISCENTE": "MESTRADO", "TOTAL": 372, "PERCENTUAL": 66.55}], "situacao_academica": [{"NM_SITUACAO_DISCENTE": "ABANDONOU", "TOTAL": 27, "PERCENTUAL": 4.83}, {"NM_SITUACAO_DISCENTE": "DESLIGADO", "TOTAL": 10, "PERCENTUAL": 1.79}, {"NM_SITUACAO_DISCENTE": "MATRICULADO", "TOTAL": 427, "PERCENTUAL": 76.39}, {"NM_SITUACAO_DISCENTE": "TITULADO", "TOTAL": 95, "PERCENTUAL": 16.99}], "internacionalizacao_nacionalidade": [{"DS_TIPO_NACIONALIDADE_DISCENTE": "BRASILEIRO", "TOTAL": 557, "PERCENTUAL": 99.64}, {"DS_TIPO_NACIONALIDADE_DISCENTE": "ESTRANGEIRO", "TOTAL": 2, "PERCENTUAL": 0.36}], "tempo_medio_titulacao": [{"DS_GRAU_ACADEMICO_DISCENTE": "DOUTORADO", "MEDIA_MESES_TITULACAO": 65.0}, {"DS_GRAU_ACADEMICO_DISCENTE": "MESTRADO", "MEDIA_MESES_TITULACAO": 33.3}], "tamanho_total_alunos_periodo": 559, "media_alunos_por_ano": 69.9, "faixa_etaria": [{"DS_FAIXA_ETARIA": "20 A 24 ANOS", "TOTAL": 48, "PERCENTUAL": 8.59}, {"DS_FAIXA_ETARIA": "25 A 29 ANOS", "TOTAL": 189, "PERCENTUAL": 33.81}, {"DS_FAIXA_ETARIA": "30 A 34 ANOS", "TOTAL": 94, "PERCENTUAL": 16.82}, {"DS_FAIXA_ETARIA": "35 A 39 ANOS", "TOTAL": 84, "PERCENTUAL": 15.03}, {"DS_FAIXA_ETARIA": "40 A 44 ANOS", "TOTAL": 75, "PERCENTUAL": 13.42}, {"DS_FAIXA_ETARIA": "45 A 49 ANOS", "TOTAL": 47, "PERCENTUAL": 8.41}, {"DS_FAIXA_ETARIA": "50 A 54 ANOS", "TOTAL": 13, "PERCENTUAL": 2.33}, {"DS_FAIXA_ETARIA": "55 A 59 ANOS", "TOTAL": 7, "PERCENTUAL": 1.25}, {"DS_FAIXA_ETARIA": "60 A 64 ANOS", "TOTAL": 2, "PERCENTUAL": 0.36}]}, "por_ano": {"2017": {"distribuicao_grau_academico": [{"DS_GRAU_ACADEMICO_DISCENTE": "DOUTORADO", "TOTAL": 16, "PERCENTUAL": 26.23}, {"DS_GRAU_ACADEMICO_DISCENTE": "MESTRADO", "TOTAL": 45, "PERCENTUAL": 73.77}], "situacao_academica": [{"NM_SITUACAO_DISCENTE": "ABANDONOU", "TOTAL": 1, "PERCENTUAL": 1.64}, {"NM_SITUACAO_DISCENTE": "DESLIGADO", "TOTAL": 1, "PERCENTUAL": 1.64}, {"NM_SITUACAO_DISCENTE": "MATRICULADO", "TOTAL": 46, "PERCENTUAL": 75.41}, {"NM_SITUACAO_DISCENTE": "TITULADO", "TOTAL": 13, "PERCENTUAL": 21.31}], "internacionalizacao_nacionalidade": [{"DS_TIPO_NACIONALIDADE_DISCENTE": "BRASILEIRO", "TOTAL": 61, "PERCENTUAL": 100.0}], "tempo_medio_titulacao": [{"DS_GRAU_ACADEMICO_DISCENTE": "MESTRADO", "MEDIA_MESES_TITULACAO": 31.8}], "tamanho_total_alunos_periodo": 61, "media_alunos_por_ano": 61.0, "faixa_etaria": [{"DS_FAIXA_ETARIA": "20 A 24 ANOS", "TOTAL": 8, "PERCENTUAL": 13.11}, {"DS_FAIXA_ETARIA": "25 A 29 ANOS", "TOTAL": 27, "PERCENTUAL": 44.26}, {"DS_FAIXA_ETARIA": "30 A 34 ANOS", "TOTAL": 12, "PERCENTUAL": 19.67}, {"DS_FAIXA_ETARIA": "35 A 39 ANOS", "TOTAL": 10, "PERCENTUAL": 16.39}, {"DS_FAIXA_ETARIA": "40 A 44 ANOS", "TOTAL": 2, "PERCENTUAL": 3.28}, {"DS_FAIXA_ETARIA": "45 A 49 ANOS", "TOTAL": 2, "PERCENTUAL": 3.28}]}, "2018": {"distribuicao_grau_academico": [{"DS_GRAU_ACADEMICO_DISCENTE": "DOUTORADO", "TOTAL": 20, "PERCENTUAL": 28.57}, {"DS_GRAU_ACADEMICO_DISCENTE": "MESTRADO", "TOTAL": 50, "PERCENTUAL": 71.43}], "situacao_academica": [{"NM_SITUACAO_DISCENTE": "ABANDONOU", "TOTAL": 4, "PERCENTUAL": 5.71}, {"NM_SITUACAO_DISCENTE": "DESLIGADO", "TOTAL": 3, "PERCENTUAL": 4.29}, {"NM_SITUACAO_DISCENTE": "MATRICULADO", "TOTAL": 53, "PERCENTUAL": 75.71}, {"NM_SITUACAO_DISCENTE": "TITULADO", "TOTAL": 10, "PERCENTUAL": 14.29}], "internacionalizacao_nacionalidade": [{"DS_TIPO_NACIONALIDADE_DISCENTE": "BRASILEIRO", "TOTAL": 70, "PERCENTUAL": 100.0}], "tempo_medio_titulacao": [{"DS_GRAU_ACADEMICO_DISCENTE": "MESTRADO", "MEDIA_MESES_TITULACAO": 32.5}], "tamanho_total_alunos_periodo": 70, "media_alunos_por_ano": 70.0, "faixa_etaria": [{"DS_FAIXA_ETARIA": "20 A 24 ANOS", "TOTAL": 5, "PERCENTUAL": 7.14}, {"DS_FAIXA_ETARIA": "25 A 29 ANOS", "TOTAL": 28, "PERCENTUAL": 40.0}, {"DS_FAIXA_ETARIA": "30 A 34 ANOS", "TOTAL": 15, "PERCENTUAL": 21.43}, {"DS_FAIXA_ETARIA": "35 A 39 ANOS", "TOTAL": 11, "PERCENTUAL": 15.71}, {"DS_FAIXA_ETARIA": "40 A 44 ANOS", "TOTAL": 7, "PERCENTUAL": 10.0}, {"DS_FAIXA_ETARIA": "45 A 49 ANOS", "TOTAL": 3, "PERCENTUAL": 4.29}, {"DS_FAIXA_ETARIA": "55 A 59 ANOS", "TOTAL": 1, "PERCENTUAL": 1.43}]}, "2019": {"distribuicao_grau_academico": [{"DS_GRAU_ACADEMICO_DISCENTE": "DOUTORADO", "TOTAL": 23, "PERCENTUAL": 31.51}, {"DS_GRAU_ACADEMICO_DISCENTE": "MESTRADO", "TOTAL": 50, "PERCENTUAL": 68.49}], "situacao_academica": [{"NM_SITUACAO_DISCENTE": "ABANDONOU", "TOTAL": 5, "PERCENTUAL": 6.85}, {"NM_SITUACAO_DISCENTE": "DESLIGADO", "TOTAL": 2, "PERCENTUAL": 2.74}, {"NM_SITUACAO_DISCENTE": "MATRICULADO", "TOTAL": 57, "PERCENTUAL": 78.08}, {"NM_SITUACAO_DISCENTE": "TITULADO", "TOTAL": 9, "PERCENTUAL": 12.33}], "internacionalizacao_nacionalidade": [{"DS_TIPO_NACIONALIDADE_DISCENTE": "BRASILEIRO", "TOTAL": 73, "PERCENTUAL": 100.0}], "tempo_medio_titulacao": [{"DS_GRAU_ACADEMICO_DISCENTE": "MESTRADO", "MEDIA_MESES_TITULACAO": 32.1}], "tamanho_total_alunos_periodo": 73, "media_alunos_por_ano": 73.0, "faixa_etaria": [{"DS_FAIXA_ETARIA": "20 A 24 ANOS", "TOTAL": 7, "PERCENTUAL": 9.59}, {"DS_FAIXA_ETARIA": "25 A 29 ANOS", "TOTAL": 30, "PERCENTUAL": 41.1}, {"DS_FAIXA_ETARIA": "30 A 34 ANOS", "TOTAL": 11, "PERCENTUAL": 15.07}, {"DS_FAIXA_ETARIA": "35 A 39 ANOS", "TOTAL": 12, "PERCENTUAL": 16.44}, {"DS_FAIXA_ETARIA": "40 A 44 ANOS", "TOTAL": 8, "PERCENTUAL": 10.96}, {"DS_FAIXA_ETARIA": "45 A 49 ANOS", "TOTAL": 5, "PERCENTUAL": 6.85}]}, "2020": {"distribuicao_grau_academico": [{"DS_GRAU_ACADEMICO_DISCENTE": "DOUTORADO", "TOTAL": 26, "PERCENTUAL": 35.62}, {"DS_GRAU_ACADEMICO_DISCENTE": "MESTRADO", "TOTAL": 47, "PERCENTUAL": 64.38}], "situacao_academica": [{"NM_SITUACAO_DISCENTE": "ABANDONOU", "TOTAL": 2, "PERCENTUAL": 2.74}, {"NM_SITUACAO_DISCENTE": "MATRICULADO", "TOTAL": 57, "PERCENTUAL": 78.08}, {"NM_SITUACAO_DISCENTE": "TITULADO", "TOTAL": 14, "PERCENTUAL": 19.18}], "internacionalizacao_nacionalidade": [{"DS_TIPO_NACIONALIDADE_DISCENTE": "BRASILEIRO", "TOTAL": 72, "PERCENTUAL": 98.63}, {"DS_TIPO_NACIONALIDADE_DISCENTE": "ESTRANGEIRO", "TOTAL": 1, "PERCENTUAL": 1.37}], "tempo_medio_titulacao": [{"DS_GRAU_ACADEMICO_DISCENTE": "DOUTORADO", "MEDIA_MESES_TITULACAO": 48.0}, {"DS_GRAU_ACADEMICO_DISCENTE": "MESTRADO", "MEDIA_MESES_TITULACAO": 31.0}], "tamanho_total_alunos_periodo": 73, "media_alunos_por_ano": 73.0, "faixa_etaria": [{"DS_FAIXA_ETARIA": "20 A 24 ANOS", "TOTAL": 3, "PERCENTUAL": 4.11}, {"DS_FAIXA_ETARIA": "25 A 29 ANOS", "TOTAL": 29, "PERCENTUAL": 39.73}, {"DS_FAIXA_ETARIA": "30 A 34 ANOS", "TOTAL": 11, "PERCENTUAL": 15.07}, {"DS_FAIXA_ETARIA": "35 A 39 ANOS", "TOTAL": 13, "PERCENTUAL": 17.81}, {"DS_FAIXA_ETARIA": "40 A 44 ANOS", "TOTAL": 11, "PERCENTUAL": 15.07}, {"DS_FAIXA_ETARIA": "45 A 49 ANOS", "TOTAL": 5, "PERCENTUAL": 6.85}, {"DS_FAIXA_ETARIA": "50 A 54 ANOS", "TOTAL": 1, "PERCENTUAL": 1.37}]}, "2021": {"distribuicao_grau_academico": [{"DS_GRAU_ACADEMICO_DISCENTE": "DOUTORADO", "TOTAL": 28, "PERCENTUAL": 35.0}, {"DS_GRAU_ACADEMICO_DISCENTE": "MESTRADO", "TOTAL": 52, "PERCENTUAL": 65.0}], "situacao_academica": [{"NM_SITUACAO_DISCENTE": "ABANDONOU", "TOTAL": 8, "PERCENTUAL": 10.0}, {"NM_SITUACAO_DISCENTE": "DESLIGADO", "TOTAL": 1, "PERCENTUAL": 1.25}, {"NM_SITUACAO_DISCENTE": "MATRICULADO", "TOTAL": 56, "PERCENTUAL": 70.0}, {"NM_SITUACAO_DISCENTE": "TITULADO", "TOTAL": 15, "PERCENTUAL": 18.75}], "internacionalizacao_nacionalidade": [{"DS_TIPO_NACIONALIDADE_DISCENTE": "BRASILEIRO", "TOTAL": 79, "PERCENTUAL": 98.75}, {"DS_TIPO_NACIONALIDADE_DISCENTE": "ESTRANGEIRO", "TOTAL": 1, "PERCENTUAL": 1.25}], "tempo_medio_titulacao": [{"DS_GRAU_ACADEMICO_DISCENTE": "DOUTORADO", "MEDIA_MESES_TITULACAO": 56.4}, {"DS_GRAU_ACADEMICO_DISCENTE": "MESTRADO", "MEDIA_MESES_TITULACAO": 31.1}], "tamanho_total_alunos_periodo": 80, "media_alunos_por_ano": 80.0, "faixa_etaria": [{"DS_FAIXA_ETARIA": "20 A 24 ANOS", "TOTAL": 8, "PERCENTUAL": 10.0}, {"DS_FAIXA_ETARIA": "25 A 29 ANOS", "TOTAL": 22, "PERCENTUAL": 27.5}, {"DS_FAIXA_ETARIA": "30 A 34 ANOS", "TOTAL": 16, "PERCENTUAL": 20.0}, {"DS_FAIXA_ETARIA": "35 A 39 ANOS", "TOTAL": 10, "PERCENTUAL": 12.5}, {"DS_FAIXA_ETARIA": "40 A 44 ANOS", "TOTAL": 15, "PERCENTUAL": 18.75}, {"DS_FAIXA_ETARIA": "45 A 49 ANOS", "TOTAL": 5, "PERCENTUAL": 6.25}, {"DS_FAIXA_ETARIA": "50 A 54 ANOS", "TOTAL": 3, "PERCENTUAL": 3.75}, {"DS_FAIXA_ETARIA": "55 A 59 ANOS", "TOTAL": 1, "PERCENTUAL": 1.25}]}, "2022": {"distribuicao_grau_academico": [{"DS_GRAU_ACADEMICO_DISCENTE": "DOUTORADO", "TOTAL": 25, "PERCENTUAL": 36.23}, {"DS_GRAU_ACADEMICO_DISCENTE": "MESTRADO", "TOTAL": 44, "PERCENTUAL": 63.77}], "situacao_academica": [{"NM_SITUACAO_DISCENTE": "ABANDONOU", "TOTAL": 3, "PERCENTUAL": 4.35}, {"NM_SITUACAO_DISCENTE": "DESLIGADO", "TOTAL": 2, "PERCENTUAL": 2.9}, {"NM_SITUACAO_DISCENTE": "MATRICULADO", "TOTAL": 56, "PERCENTUAL": 81.16}, {"NM_SITUACAO_DISCENTE": "TITULADO", "TOTAL": 8, "PERCENTUAL": 11.59}], "internacionalizacao_nacionalidade": [{"DS_TIPO_NACIONALIDADE_DISCENTE": "BRASILEIRO", "TOTAL": 69, "PERCENTUAL": 100.0}], "tempo_medio_titulacao": [{"DS_GRAU_ACADEMICO_DISCENTE": "DOUTORADO", "MEDIA_MESES_TITULACAO": 76.0}, {"DS_GRAU_ACADEMICO_DISCENTE": "MESTRADO", "MEDIA_MESES_TITULACAO": 39.7}], "tamanho_total_alunos_periodo": 69, "media_alunos_por_ano": 69.0, "faixa_etaria": [{"DS_FAIXA_ETARIA": "20 A 24 ANOS", "TOTAL": 7, "PERCENTUAL": 10.14}, {"DS_FAIXA_ETARIA": "25 A 29 ANOS", "TOTAL": 16, "PERCENTUAL": 23.19}, {"DS_FAIXA_ETARIA": "30 A 34 ANOS", "TOTAL": 11, "PERCENTUAL": 15.94}, {"DS_FAIXA_ETARIA": "35 A 39 ANOS", "TOTAL": 11, "PERCENTUAL": 15.94}, {"DS_FAIXA_ETARIA": "40 A 44 ANOS", "TOTAL": 13, "PERCENTUAL": 18.84}, {"DS_FAIXA_ETARIA": "45 A 49 ANOS", "TOTAL": 7, "PERCENTUAL": 10.14}, {"DS_FAIXA_ETARIA": "50 A 54 ANOS", "TOTAL": 2, "PERCENTUAL": 2.9}, {"DS_FAIXA_ETARIA": "55 A 59 ANOS", "TOTAL": 2, "PERCENTUAL": 2.9}]}, "2023": {"distribuicao_grau_academico": [{"DS_GRAU_ACADEMICO_DISCENTE": "DOUTORADO", "TOTAL": 26, "PERCENTUAL": 38.81}, {"DS_GRAU_ACADEMICO_DISCENTE": "MESTRADO", "TOTAL": 41, "PERCENTUAL": 61.19}], "situacao_academica": [{"NM_SITUACAO_DISCENTE": "ABANDONOU", "TOTAL": 3, "PERCENTUAL": 4.48}, {"NM_SITUACAO_DISCENTE": "DESLIGADO", "TOTAL": 1, "PERCENTUAL": 1.49}, {"NM_SITUACAO_DISCENTE": "MATRICULADO", "TOTAL": 52, "PERCENTUAL": 77.61}, {"NM_SITUACAO_DISCENTE": "TITULADO", "TOTAL": 11, "PERCENTUAL": 16.42}], "internacionalizacao_nacionalidade": [{"DS_TIPO_NACIONALIDADE_DISCENTE": "BRASILEIRO", "TOTAL": 67, "PERCENTUAL": 100.0}], "tempo_medio_titulacao": [{"DS_GRAU_ACADEMICO_DISCENTE": "DOUTORADO", "MEDIA_MESES_TITULACAO": 64.0}, {"DS_GRAU_ACADEMICO_DISCENTE": "MESTRADO", "MEDIA_MESES_TITULACAO": 33.0}], "tamanho_total_alunos_periodo": 67, "media_alunos_por_ano": 67.0, "faixa_etaria": [{"DS_FAIXA_ETARIA": "20 A 24 ANOS", "TOTAL": 6, "PERCENTUAL": 8.96}, {"DS_FAIXA_ETARIA": "25 A 29 ANOS", "TOTAL": 18, "PERCENTUAL": 26.87}, {"DS_FAIXA_ETARIA": "30 A 34 ANOS", "TOTAL": 7, "PERCENTUAL": 10.45}, {"DS_FAIXA_ETARIA": "35 A 39 ANOS", "TOTAL": 11, "PERCENTUAL": 16.42}, {"DS_FAIXA_ETARIA": "40 A 44 ANOS", "TOTAL": 12, "PERCENTUAL": 17.91}, {"DS_FAIXA_ETARIA": "45 A 49 ANOS", "TOTAL": 8, "PERCENTUAL": 11.94}, {"DS_FAIXA_ETARIA": "50 A 54 ANOS", "TOTAL": 3, "PERCENTUAL": 4.48}, {"DS_FAIXA_ETARIA": "55 A 59 ANOS", "TOTAL": 2, "PERCENTUAL": 2.99}]}, "2024": {"distribuicao_grau_academico": [{"DS_GRAU_ACADEMICO_DISCENTE": "DOUTORADO", "TOTAL": 23, "PERCENTUAL": 34.85}, {"DS_GRAU_ACADEMICO_DISCENTE": "MESTRADO", "TOTAL": 43, "PERCENTUAL": 65.15}], "situacao_academica": [{"NM_SITUACAO_DISCENTE": "ABANDONOU", "TOTAL": 1, "PERCENTUAL": 1.52}, {"NM_SITUACAO_DISCENTE": "MATRICULADO", "TOTAL": 50, "PERCENTUAL": 75.76}, {"NM_SITUACAO_DISCENTE": "TITULADO", "TOTAL": 15, "PERCENTUAL": 22.73}], "internacionalizacao_nacionalidade": [{"DS_TIPO_NACIONALIDADE_DISCENTE": "BRASILEIRO", "TOTAL": 66, "PERCENTUAL": 100.0}], "tempo_medio_titulacao": [{"DS_GRAU_ACADEMICO_DISCENTE": "DOUTORADO", "MEDIA_MESES_TITULACAO": 78.2}, {"DS_GRAU_ACADEMICO_DISCENTE": "MESTRADO", "MEDIA_MESES_TITULACAO": 37.4}], "tamanho_total_alunos_periodo": 66, "media_alunos_por_ano": 66.0, "faixa_etaria": [{"DS_FAIXA_ETARIA": "20 A 24 ANOS", "TOTAL": 4, "PERCENTUAL": 6.06}, {"DS_FAIXA_ETARIA": "25 A 29 ANOS", "TOTAL": 19, "PERCENTUAL": 28.79}, {"DS_FAIXA_ETARIA": "30 A 34 ANOS", "TOTAL": 11, "PERCENTUAL": 16.67}, {"DS_FAIXA_ETARIA": "35 A 39 ANOS", "TOTAL": 6, "PERCENTUAL": 9.09}, {"DS_FAIXA_ETARIA": "40 A 44 ANOS", "TOTAL": 7, "PERCENTUAL": 10.61}, {"DS_FAIXA_ETARIA": "45 A 49 ANOS", "TOTAL": 12, "PERCENTUAL": 18.18}, {"DS_FAIXA_ETARIA": "50 A 54 ANOS", "TOTAL": 4, "PERCENTUAL": 6.06}, {"DS_FAIXA_ETARIA": "55 A 59 ANOS", "TOTAL": 1, "PERCENTUAL": 1.52}, {"DS_FAIXA_ETARIA": "60 A 64 ANOS", "TOTAL": 2, "PERCENTUAL": 3.03}]}}}, "docentes": {"geral": {"lideranca_bolsas_pq": [{"TEM_BOLSA_PQ": "NÃO", "TOTAL": 58, "PERCENTUAL": 61.05}, {"TEM_BOLSA_PQ": "SIM", "TOTAL": 37, "PERCENTUAL": 38.95}], "internacionalizacao_titulacao_exterior": [{"TITULADO_NO_EXTERIOR": "NÃO", "TOTAL": 81, "PERCENTUAL": 85.26}, {"TITULADO_NO_EXTERIOR": "SIM", "TOTAL": 14, "PERCENTUAL": 14.74}], "internacionalizacao_nacionalidade": [{"DOCENTE_ESTRANGEIRO": "BRASILEIRO", "TOTAL": 91, "PERCENTUAL": 95.79}, {"DOCENTE_ESTRANGEIRO": "ESTRANGEIRO", "TOTAL": 4, "PERCENTUAL": 4.21}], "endogamia_academica": [{"ENDOGAMIA": "NÃO", "TOTAL": 95, "PERCENTUAL": 100.0}], "maturidade_media_anos_doutorado": 16.4, "categoria_docente": [{"DS_CATEGORIA_DOCENTE": "COLABORADOR", "TOTAL": 7, "PERCENTUAL": 6.86}, {"DS_CATEGORIA_DOCENTE": "PERMANENTE", "TOTAL": 95, "PERCENTUAL": 93.14}], "regime_trabalho": [{"DS_REGIME_TRABALHO": "INTEGRAL", "TOTAL": 95, "PERCENTUAL": 100.0}]}, "por_ano": {"2017": {"lideranca_bolsas_pq": [{"TEM_BOLSA_PQ": "NÃO", "TOTAL": 7, "PERCENTUAL": 63.64}, {"TEM_BOLSA_PQ": "SIM", "TOTAL": 4, "PERCENTUAL": 36.36}], "internacionalizacao_titulacao_exterior": [{"TITULADO_NO_EXTERIOR": "NÃO", "TOTAL": 10, "PERCENTUAL": 90.91}, {"TITULADO_NO_EXTERIOR": "SIM", "TOTAL": 1, "PERCENTUAL": 9.09}], "internacionalizacao_nacionalidade": [{"DOCENTE_ESTRANGEIRO": "BRASILEIRO", "TOTAL": 11, "PERCENTUAL": 100.0}], "endogamia_academica": [{"ENDOGAMIA": "NÃO", "TOTAL": 11, "PERCENTUAL": 100.0}], "maturidade_media_anos_doutorado": 11.7, "categoria_docente": [{"DS_CATEGORIA_DOCENTE": "COLABORADOR", "TOTAL": 1, "PERCENTUAL": 8.33}, {"DS_CATEGORIA_DOCENTE": "PERMANENTE", "TOTAL": 11, "PERCENTUAL": 91.67}], "regime_trabalho": [{"DS_REGIME_TRABALHO": "INTEGRAL", "TOTAL": 11, "PERCENTUAL": 100.0}]}, "2018": {"lideranca_bolsas_pq": [{"TEM_BOLSA_PQ": "NÃO", "TOTAL": 7, "PERCENTUAL": 63.64}, {"TEM_BOLSA_PQ": "SIM", "TOTAL": 4, "PERCENTUAL": 36.36}], "internacionalizacao_titulacao_exterior": [{"TITULADO_NO_EXTERIOR": "NÃO", "TOTAL": 10, "PERCENTUAL": 90.91}, {"TITULADO_NO_EXTERIOR": "SIM", "TOTAL": 1, "PERCENTUAL": 9.09}], "internacionalizacao_nacionalidade": [{"DOCENTE_ESTRANGEIRO": "BRASILEIRO", "TOTAL": 11, "PERCENTUAL": 100.0}], "endogamia_academica": [{"ENDOGAMIA": "NÃO", "TOTAL": 11, "PERCENTUAL": 100.0}], "maturidade_media_anos_doutorado": 12.7, "categoria_docente": [{"DS_CATEGORIA_DOCENTE": "COLABORADOR", "TOTAL": 1, "PERCENTUAL": 8.33}, {"DS_CATEGORIA_DOCENTE": "PERMANENTE", "TOTAL": 11, "PERCENTUAL": 91.67}], "regime_trabalho": [{"DS_REGIME_TRABALHO": "INTEGRAL", "TOTAL": 11, "PERCENTUAL": 100.0}]}, "2019": {"lideranca_bolsas_pq": [{"TEM_BOLSA_PQ": "NÃO", "TOTAL": 7, "PERCENTUAL": 58.33}, {"TEM_BOLSA_PQ": "SIM", "TOTAL": 5, "PERCENTUAL": 41.67}], "internacionalizacao_titulacao_exterior": [{"TITULADO_NO_EXTERIOR": "NÃO", "TOTAL": 10, "PERCENTUAL": 83.33}, {"TITULADO_NO_EXTERIOR": "SIM", "TOTAL": 2, "PERCENTUAL": 16.67}], "internacionalizacao_nacionalidade": [{"DOCENTE_ESTRANGEIRO": "BRASILEIRO", "TOTAL": 12, "PERCENTUAL": 100.0}], "endogamia_academica": [{"ENDOGAMIA": "NÃO", "TOTAL": 12, "PERCENTUAL": 100.0}], "maturidade_media_anos_doutorado": 13.2, "categoria_docente": [{"DS_CATEGORIA_DOCENTE": "PERMANENTE", "TOTAL": 12, "PERCENTUAL": 100.0}], "regime_trabalho": [{"DS_REGIME_TRABALHO": "INTEGRAL", "TOTAL": 12, "PERCENTUAL": 100.0}]}, "2020": {"lideranca_bolsas_pq": [{"TEM_BOLSA_PQ": "NÃO", "TOTAL": 8, "PERCENTUAL": 66.67}, {"TEM_BOLSA_PQ": "SIM", "TOTAL": 4, "PERCENTUAL": 33.33}], "internacionalizacao_titulacao_exterior": [{"TITULADO_NO_EXTERIOR": "NÃO", "TOTAL": 10, "PERCENTUAL": 83.33}, {"TITULADO_NO_EXTERIOR": "SIM", "TOTAL": 2, "PERCENTUAL": 16.67}], "internacionalizacao_nacionalidade": [{"DOCENTE_ESTRANGEIRO": "BRASILEIRO", "TOTAL": 12, "PERCENTUAL": 100.0}], "endogamia_academica": [{"ENDOGAMIA": "NÃO", "TOTAL": 12, "PERCENTUAL": 100.0}], "maturidade_media_anos_doutorado": 14.2, "categoria_docente": [{"DS_CATEGORIA_DOCENTE": "PERMANENTE", "TOTAL": 12, "PERCENTUAL": 100.0}], "regime_trabalho": [{"DS_REGIME_TRABALHO": "INTEGRAL", "TOTAL": 12, "PERCENTUAL": 100.0}]}, "2021": {"lideranca_bolsas_pq": [{"TEM_BOLSA_PQ": "NÃO", "TOTAL": 7, "PERCENTUAL": 58.33}, {"TEM_BOLSA_PQ": "SIM", "TOTAL": 5, "PERCENTUAL": 41.67}], "internacionalizacao_titulacao_exterior": [{"TITULADO_NO_EXTERIOR": "NÃO", "TOTAL": 10, "PERCENTUAL": 83.33}, {"TITULADO_NO_EXTERIOR": "SIM", "TOTAL": 2, "PERCENTUAL": 16.67}], "internacionalizacao_nacionalidade": [{"DOCENTE_ESTRANGEIRO": "BRASILEIRO", "TOTAL": 11, "PERCENTUAL": 91.67}, {"DOCENTE_ESTRANGEIRO": "ESTRANGEIRO", "TOTAL": 1, "PERCENTUAL": 8.33}], "endogamia_academica": [{"ENDOGAMIA": "NÃO", "TOTAL": 12, "PERCENTUAL": 100.0}], "maturidade_media_anos_doutorado": 17.8, "categoria_docente": [{"DS_CATEGORIA_DOCENTE": "COLABORADOR", "TOTAL": 2, "PERCENTUAL": 14.29}, {"DS_CATEGORIA_DOCENTE": "PERMANENTE", "TOTAL": 12, "PERCENTUAL": 85.71}], "regime_trabalho": [{"DS_REGIME_TRABALHO": "INTEGRAL", "TOTAL": 12, "PERCENTUAL": 100.0}]}, "2022": {"lideranca_bolsas_pq": [{"TEM_BOLSA_PQ": "NÃO", "TOTAL": 7, "PERCENTUAL": 58.33}, {"TEM_BOLSA_PQ": "SIM", "TOTAL": 5, "PERCENTUAL": 41.67}], "internacionalizacao_titulacao_exterior": [{"TITULADO_NO_EXTERIOR": "NÃO", "TOTAL": 10, "PERCENTUAL": 83.33}, {"TITULADO_NO_EXTERIOR": "SIM", "TOTAL": 2, "PERCENTUAL": 16.67}], "internacionalizacao_nacionalidade": [{"DOCENTE_ESTRANGEIRO": "BRASILEIRO", "TOTAL": 11, "PERCENTUAL": 91.67}, {"DOCENTE_ESTRANGEIRO": "ESTRANGEIRO", "TOTAL": 1, "PERCENTUAL": 8.33}], "endogamia_academica": [{"ENDOGAMIA": "NÃO", "TOTAL": 12, "PERCENTUAL": 100.0}], "maturidade_media_anos_doutorado": 19.2, "categoria_docente": [{"DS_CATEGORIA_DOCENTE": "COLABORADOR", "TOTAL": 1, "PERCENTUAL": 7.69}, {"DS_CATEGORIA_DOCENTE": "PERMANENTE", "TOTAL": 12, "PERCENTUAL": 92.31}], "regime_trabalho": [{"DS_REGIME_TRABALHO": "INTEGRAL", "TOTAL": 12, "PERCENTUAL": 100.0}]}, "2023": {"lideranca_bolsas_pq": [{"TEM_BOLSA_PQ": "NÃO", "TOTAL": 8, "PERCENTUAL": 61.54}, {"TEM_BOLSA_PQ": "SIM", "TOTAL": 5, "PERCENTUAL": 38.46}], "internacionalizacao_titulacao_exterior": [{"TITULADO_NO_EXTERIOR": "NÃO", "TOTAL": 11, "PERCENTUAL": 84.62}, {"TITULADO_NO_EXTERIOR": "SIM", "TOTAL": 2, "PERCENTUAL": 15.38}], "internacionalizacao_nacionalidade": [{"DOCENTE_ESTRANGEIRO": "BRASILEIRO", "TOTAL": 12, "PERCENTUAL": 92.31}, {"DOCENTE_ESTRANGEIRO": "ESTRANGEIRO", "TOTAL": 1, "PERCENTUAL": 7.69}], "endogamia_academica": [{"ENDOGAMIA": "NÃO", "TOTAL": 13, "PERCENTUAL": 100.0}], "maturidade_media_anos_doutorado": 20.5, "categoria_docente": [{"DS_CATEGORIA_DOCENTE": "PERMANENTE", "TOTAL": 13, "PERCENTUAL": 100.0}], "regime_trabalho": [{"DS_REGIME_TRABALHO": "INTEGRAL", "TOTAL": 13, "PERCENTUAL": 100.0}]}, "2024": {"lideranca_bolsas_pq": [{"TEM_BOLSA_PQ": "NÃO", "TOTAL": 7, "PERCENTUAL": 58.33}, {"TEM_BOLSA_PQ": "SIM", "TOTAL": 5, "PERCENTUAL": 41.67}], "internacionalizacao_titulacao_exterior": [{"TITULADO_NO_EXTERIOR": "NÃO", "TOTAL": 10, "PERCENTUAL": 83.33}, {"TITULADO_NO_EXTERIOR": "SIM", "TOTAL": 2, "PERCENTUAL": 16.67}], "internacionalizacao_nacionalidade": [{"DOCENTE_ESTRANGEIRO": "BRASILEIRO", "TOTAL": 11, "PERCENTUAL": 91.67}, {"DOCENTE_ESTRANGEIRO": "ESTRANGEIRO", "TOTAL": 1, "PERCENTUAL": 8.33}], "endogamia_academica": [{"ENDOGAMIA": "NÃO", "TOTAL": 12, "PERCENTUAL": 100.0}], "maturidade_media_anos_doutorado": 21.2, "categoria_docente": [{"DS_CATEGORIA_DOCENTE": "COLABORADOR", "TOTAL": 2, "PERCENTUAL": 14.29}, {"DS_CATEGORIA_DOCENTE": "PERMANENTE", "TOTAL": 12, "PERCENTUAL": 85.71}], "regime_trabalho": [{"DS_REGIME_TRABALHO": "INTEGRAL", "TOTAL": 12, "PERCENTUAL": 100.0}]}}}, "producao": {"geral": {"total_publicacoes": 202, "media_publicacoes_por_ano": 25.2, "distribuicao_subtipo": [{"NM_SUBTIPO_PRODUCAO": "ARTIGO EM PERIÓDICO", "TOTAL": 202, "PERCENTUAL": 100.0}], "top_veiculos": [{"DS_TITULO_PADRONIZADO": "IEEE ACCESS", "TOTAL": 7}, {"DS_TITULO_PADRONIZADO": "JOURNAL OF HEALTH INFORMATICS", "TOTAL": 6}, {"DS_TITULO_PADRONIZADO": "REVISTA IEEE AMÉRICA LATINA", "TOTAL": 6}, {"DS_TITULO_PADRONIZADO": "BRAZILIAN JOURNAL OF DEVELOPMENT", "TOTAL": 5}, {"DS_TITULO_PADRONIZADO": "PATTERN RECOGNITION LETTERS", "TOTAL": 5}, {"DS_TITULO_PADRONIZADO": "CONCURRENCY AND COMPUTATION: PRACTICE & EXPERIENCE", "TOTAL": 5}, {"DS_TITULO_PADRONIZADO": "JOURNAL OF INTERNET SERVICES AND APPLICATIONS", "TOTAL": 4}, {"DS_TITULO_PADRONIZADO": "SOCIAL INDICATORS RESEARCH", "TOTAL": 4}, {"DS_TITULO_PADRONIZADO": "METHODSX", "TOTAL": 3}, {"DS_TITULO_PADRONIZADO": "INTERNATIONAL JOURNAL OF COMPUTER ARCHITECTURE EDUCATION", "TOTAL": 3}]}, "por_ano": {"2017": {"total_publicacoes": 16, "media_publicacoes_por_ano": 16.0, "distribuicao_subtipo": [{"NM_SUBTIPO_PRODUCAO": "ARTIGO EM PERIÓDICO", "TOTAL": 16, "PERCENTUAL": 100.0}], "top_veiculos": [{"DS_TITULO_PADRONIZADO": "CONCURRENCY AND COMPUTATION: PRACTICE & EXPERIENCE", "TOTAL": 2}, {"DS_TITULO_PADRONIZADO": "APPLIED ARTIFICIAL INTELLIGENCE", "TOTAL": 1}, {"DS_TITULO_PADRONIZADO": "WILEY INTERDISCIPLINARY REVIEWS: DATA MINING AND KNOWLEDGE DISCOVERY", "TOTAL": 1}, {"DS_TITULO_PADRONIZADO": "INFORMATICS IN EDUCATION", "TOTAL": 1}, {"DS_TITULO_PADRONIZADO": "ISYS: REVISTA BRASILEIRA DE SISTEMAS DE INFORMAÇÃO", "TOTAL": 1}, {"DS_TITULO_PADRONIZADO": "MULTIMEDIA TOOLS AND APPLICATIONS", "TOTAL": 1}, {"DS_TITULO_PADRONIZADO": "ABAKÓS", "TOTAL": 1}, {"DS_TITULO_PADRONIZADO": "REVISTA BRASILEIRA DE COMPUTAÇÃO APLICADA", "TOTAL": 1}, {"DS_TITULO_PADRONIZADO": "REVISTA DE SISTEMAS E COMPUTAÇÃO - RSC", "TOTAL": 1}, {"DS_TITULO_PADRONIZADO": "REVISTA IEEE AMÉRICA LATINA", "TOTAL": 1}]}, "2018": {"total_publicacoes": 18, "media_publicacoes_por_ano": 18.0, "distribuicao_subtipo": [{"NM_SUBTIPO_PRODUCAO": "ARTIGO EM PERIÓDICO", "TOTAL": 18, "PERCENTUAL": 100.0}], "top_veiculos": [{"DS_TITULO_PADRONIZADO": "INTERNATIONAL JOURNAL OF WEB INFORMATION SYSTEMS (PRINT)", "TOTAL": 2}, {"DS_TITULO_PADRONIZADO": "INTERNATIONAL JOURNAL OF COMPUTER ARCHITECTURE EDUCATION", "TOTAL": 1}, {"DS_TITULO_PADRONIZADO": "INFORMATICS IN EDUCATION", "TOTAL": 1}, {"DS_TITULO_PADRONIZADO": "REVISTA ELETRÔNICA DE INICIAÇÃO CIENTÍFICA", "TOTAL": 1}, {"DS_TITULO_PADRONIZADO": "PERSPECTIVAS EM CIÊNCIA DA INFORMAÇÃO", "TOTAL": 1}, {"DS_TITULO_PADRONIZADO": "IET SOFTWARE (PRINT)", "TOTAL": 1}, {"DS_TITULO_PADRONIZADO": "TELEMATICS AND INFORMATICS", "TOTAL": 1}, {"DS_TITULO_PADRONIZADO": "ACM TRANSACTIONS ON ACCESSIBLE COMPUTING (TACCESS)", "TOTAL": 1}, {"DS_TITULO_PADRONIZADO": "JOURNAL OF INFORMATION AND DATA MANAGEMENT", "TOTAL": 1}, {"DS_TITULO_PADRONIZADO": "IEEE TRANSACTIONS ON IMAGE PROCESSING", "TOTAL": 1}]}, "2019": {"total_publicacoes": 19, "media_publicacoes_por_ano": 19.0, "distribuicao_subtipo": [{"NM_SUBTIPO_PRODUCAO": "ARTIGO EM PERIÓDICO", "TOTAL": 19, "PERCENTUAL": 100.0}], "top_veiculos": [{"DS_TITULO_PADRONIZADO": "BRAZILIAN JOURNAL OF DEVELOPMENT", "TOTAL": 2}, {"DS_TITULO_PADRONIZADO": "REVISTA IEEE AMÉRICA LATINA", "TOTAL": 2}, {"DS_TITULO_PADRONIZADO": "CONCURRENCY AND COMPUTATION: PRACTICE & EXPERIENCE", "TOTAL": 1}, {"DS_TITULO_PADRONIZADO": "JOURNAL OF COMPUTATIONAL BIOLOGY", "TOTAL": 1}, {"DS_TITULO_PADRONIZADO": "INFORMÁTICA NA EDUCAÇÃO", "TOTAL": 1}, {"DS_TITULO_PADRONIZADO": "SENSORS (BASEL)", "TOTAL": 1}, {"DS_TITULO_PADRONIZADO": "EXPERT SYSTEMS WITH APPLICATIONS", "TOTAL": 1}, {"DS_TITULO_PADRONIZADO": "IEEE ACCESS", "TOTAL": 1}, {"DS_TITULO_PADRONIZADO": "INTERNATIONAL JOURNAL OF PATTERN RECOGNITION AND ARTIFICIAL INTELLIGENCE", "TOTAL": 1}, {"DS_TITULO_PADRONIZADO": "JOURNAL OF INFORMATION AND DATA MANAGEMENT - JIDM", "TOTAL": 1}]}, "2020": {"total_publicacoes": 21, "media_publicacoes_por_ano": 21.0, "distribuicao_subtipo": [{"NM_SUBTIPO_PRODUCAO": "ARTIGO EM PERIÓDICO", "TOTAL": 21, "PERCENTUAL": 100.0}], "top_veiculos": [{"DS_TITULO_PADRONIZADO": "IEEE ACCESS", "TOTAL": 3}, {"DS_TITULO_PADRONIZADO": "PATTERN RECOGNITION LETTERS", "TOTAL": 3}, {"DS_TITULO_PADRONIZADO": "REVISTA IEEE AMÉRICA LATINA", "TOTAL": 2}, {"DS_TITULO_PADRONIZADO": "INTERNATIONAL JOURNAL OF INFORMATION AND LEARNING TECHNOLOGY", "TOTAL": 1}, {"DS_TITULO_PADRONIZADO": "BRAZILIAN JOURNAL OF DEVELOPMENT", "TOTAL": 1}, {"DS_TITULO_PADRONIZADO": "IEEE EMBEDDED SYSTEMS LETTERS (IMPRESSO)", "TOTAL": 1}, {"DS_TITULO_PADRONIZADO": "INTELLIGENT DATA ANALYSIS (PRINT)", "TOTAL": 1}, {"DS_TITULO_PADRONIZADO": "VEHICULAR COMMUNICATIONS", "TOTAL": 1}, {"DS_TITULO_PADRONIZADO": "MULTIMEDIA TOOLS AND APPLICATIONS", "TOTAL": 1}, {"DS_TITULO_PADRONIZADO": "PATTERN RECOGNITION", "TOTAL": 1}]}, "2021": {"total_publicacoes": 23, "media_publicacoes_por_ano": 23.0, "distribuicao_subtipo": [{"NM_SUBTIPO_PRODUCAO": "ARTIGO EM PERIÓDICO", "TOTAL": 23, "PERCENTUAL": 100.0}], "top_veiculos": [{"DS_TITULO_PADRONIZADO": "INFORMATION SCIENCES", "TOTAL": 2}, {"DS_TITULO_PADRONIZADO": "BRAZILIAN JOURNAL OF DEVELOPMENT", "TOTAL": 2}, {"DS_TITULO_PADRONIZADO": "PROFESSIONAL GEOGRAPHER", "TOTAL": 1}, {"DS_TITULO_PADRONIZADO": "CONCURRENCY AND COMPUTATION: PRACTICE & EXPERIENCE", "TOTAL": 1}, {"DS_TITULO_PADRONIZADO": "ABAKÓS", "TOTAL": 1}, {"DS_TITULO_PADRONIZADO": "IEEE EMBEDDED SYSTEMS LETTERS (IMPRESSO)", "TOTAL": 1}, {"DS_TITULO_PADRONIZADO": "ENTERTAINMENT COMPUTING", "TOTAL": 1}, {"DS_TITULO_PADRONIZADO": "ISYS: REVISTA BRASILEIRA DE SISTEMAS DE INFORMAÇÃO", "TOTAL": 1}, {"DS_TITULO_PADRONIZADO": "SOCIAL NETWORK ANALYSIS AND MINING", "TOTAL": 1}, {"DS_TITULO_PADRONIZADO": "INTERNATIONAL JOURNAL OF BIOINFORMATICS RESEARCH AND APPLICATIONS (PRINT)", "TOTAL": 1}]}, "2022": {"total_publicacoes": 23, "media_publicacoes_por_ano": 23.0, "distribuicao_subtipo": [{"NM_SUBTIPO_PRODUCAO": "ARTIGO EM PERIÓDICO", "TOTAL": 23, "PERCENTUAL": 100.0}], "top_veiculos": [{"DS_TITULO_PADRONIZADO": "ARTIFICIAL INTELLIGENCE REVIEW", "TOTAL": 1}, {"DS_TITULO_PADRONIZADO": "REVISTA BRASILEIRA EM TECNOLOGIA DA INFORMAÇÃO", "TOTAL": 1}, {"DS_TITULO_PADRONIZADO": "JOURNAL OF HEALTH INFORMATICS", "TOTAL": 1}, {"DS_TITULO_PADRONIZADO": "ANNALS OF MATHEMATICS AND ARTIFICIAL INTELLIGENCE", "TOTAL": 1}, {"DS_TITULO_PADRONIZADO": "SOCIAL INDICATORS RESEARCH", "TOTAL": 1}, {"DS_TITULO_PADRONIZADO": "CADERNO DE GEOGRAFIA", "TOTAL": 1}, {"DS_TITULO_PADRONIZADO": "REMOTE SENSING APPLICATIONS: SOCIETY AND ENVIRONMENT", "TOTAL": 1}, {"DS_TITULO_PADRONIZADO": "JOURNAL OF INTERNET SERVICES AND APPLICATIONS", "TOTAL": 1}, {"DS_TITULO_PADRONIZADO": "HUMAN VACCINES & IMMUNOTHERAPEUTICS", "TOTAL": 1}, {"DS_TITULO_PADRONIZADO": "TECHNOLOGY AUDIT AND PRODUCTION RESERVES (ONLINE)", "TOTAL": 1}]}, "2023": {"total_publicacoes": 31, "media_publicacoes_por_ano": 31.0, "distribuicao_subtipo": [{"NM_SUBTIPO_PRODUCAO": "ARTIGO EM PERIÓDICO", "TOTAL": 31, "PERCENTUAL": 100.0}], "top_veiculos": [{"DS_TITULO_PADRONIZADO": "ENERGIES (BASEL)", "TOTAL": 2}, {"DS_TITULO_PADRONIZADO": "SUSTAINABILITY (BASEL)", "TOTAL": 1}, {"DS_TITULO_PADRONIZADO": "INTERNATIONAL JOURNAL OF COMPUTER ARCHITECTURE EDUCATION", "TOTAL": 1}, {"DS_TITULO_PADRONIZADO": "EXPERT SYSTEMS (ONLINE)", "TOTAL": 1}, {"DS_TITULO_PADRONIZADO": "CONCILIUM ENGLISH EDITION", "TOTAL": 1}, {"DS_TITULO_PADRONIZADO": "REVISTA IEEE AMÉRICA LATINA", "TOTAL": 1}, {"DS_TITULO_PADRONIZADO": "RB. RADIOLOGIA BRASILEIRA", "TOTAL": 1}, {"DS_TITULO_PADRONIZADO": "SN BUSINESS & ECONOMICS", "TOTAL": 1}, {"DS_TITULO_PADRONIZADO": "INFORMATION DISCOVERY AND DELIVERY (PRINT)", "TOTAL": 1}, {"DS_TITULO_PADRONIZADO": "INTERNATIONAL JOURNAL OF PROCUREMENT MANAGEMENT", "TOTAL": 1}]}, "2024": {"total_publicacoes": 51, "media_publicacoes_por_ano": 51.0, "distribuicao_subtipo": [{"NM_SUBTIPO_PRODUCAO": "ARTIGO EM PERIÓDICO", "TOTAL": 51, "PERCENTUAL": 100.0}], "top_veiculos": [{"DS_TITULO_PADRONIZADO": "JOURNAL OF HEALTH INFORMATICS", "TOTAL": 5}, {"DS_TITULO_PADRONIZADO": "SOCIAL INDICATORS RESEARCH", "TOTAL": 2}, {"DS_TITULO_PADRONIZADO": "IEEE ACCESS", "TOTAL": 2}, {"DS_TITULO_PADRONIZADO": "JOURNAL OF INTERNET SERVICES AND APPLICATIONS", "TOTAL": 2}, {"DS_TITULO_PADRONIZADO": "ENGINEERING APPLICATIONS OF ARTIFICIAL INTELLIGENCE", "TOTAL": 1}, {"DS_TITULO_PADRONIZADO": "METHODSX", "TOTAL": 1}, {"DS_TITULO_PADRONIZADO": "JOURNAL OF INTELLIGENT & FUZZY SYSTEMS", "TOTAL": 1}, {"DS_TITULO_PADRONIZADO": "PROCESSES", "TOTAL": 1}, {"DS_TITULO_PADRONIZADO": "IEEE TRANSACTIONS ON INTELLIGENT VEHICLES", "TOTAL": 1}, {"DS_TITULO_PADRONIZADO": "ARTIFICIAL INTELLIGENCE REVIEW (DORDRECHT. ONLINE)", "TOTAL": 1}]}}}}